main.py
models.py
predict.py
train.py
worldbank/__init__.py
worldbank/api.py
worldbank/getter.py
worldbank_senegal_sylla-0.1.0.dist-info/METADATA
worldbank_senegal_sylla-0.1.0.dist-info/WHEEL
worldbank_senegal_sylla-0.1.0.dist-info/top_level.txt
worldbank_senegal_sylla-0.1.0.dist-info/RECORD
