Metadata-Version: 2.4
Name: worldbank-senegal-sylla
Version: 0.1.0
Summary: Analyse des données économiques du Sénégal avec l'API World Bank
Requires-Python: >=3.8
